rockwren/__init__.py
rockwren/accesspoint.py
rockwren/controls.html
rockwren/env.py
rockwren/favicon.svg
rockwren/index.html
rockwren/information.html
rockwren/jsondb.py
rockwren/mqtt_client.py
rockwren/mqtt_config.html
rockwren/networking.py
rockwren/page_not_found.html
rockwren/restart.html
rockwren/rockwren.py
rockwren/secrets.py
rockwren/style.css
rockwren/utils.py
rockwren/version.py
rockwren/viewlogs.html
rockwren/web.py
rockwren/wifi_config.html
rockwren/wifi_setup.html
micropython_rockwren-1.0.0.dist-info/METADATA
micropython_rockwren-1.0.0.dist-info/WHEEL
micropython_rockwren-1.0.0.dist-info/top_level.txt
micropython_rockwren-1.0.0.dist-info/RECORD
