Metadata-Version: 2.1
Name: micropython-rockwren
Version: 1.0.0
Summary: Device framework (MQTT, Web) for MicroPython on the ESP8266 and Pico W.
Home-page: https://github.com/ccrighton/rockwren
Author: Charlie Crighton
Author-email: code@crighton.net.nz
Maintainer: Charlie Crighton
Maintainer-email: code@crighton.net.nz
License: GPLv3-or-later
Project-URL: GitHub, https://github.com/ccrighton/rockwren
Requires-Dist: micropython-umqtt.simple2 ==2.2.0
Requires-Dist: micropython-umqtt.robust2 ==2.2.0
Requires-Dist: micropython-ccrighton-phew
